Metadata-Version: 2.4
Name: ibpc
Version: 0.0.6
Summary: An entrypoint for the Industrial Bin Picking Challenge
Home-page: https://bpc.opencv.org/
Author: Tully Foote
Author-email: tullyfoote@intrinsic.ai
License: Apache 2.0
Requires-Dist: empy
Requires-Dist: rocker>=0.2.18
Dynamic: author
Dynamic: author-email
Dynamic: description
Dynamic: description-content-type
Dynamic: home-page
Dynamic: license
Dynamic: requires-dist
Dynamic: summary
